setup.py
eudtrg/LICENSE.py
eudtrg/__init__.py
eudtrg.egg-info/PKG-INFO
eudtrg.egg-info/SOURCES.txt
eudtrg.egg-info/dependency_links.txt
eudtrg.egg-info/top_level.txt
eudtrg/base/__init__.py
eudtrg/base/stocktrg.py
eudtrg/base/trgconst.py
eudtrg/base/trgstrconst.py
eudtrg/base/dataspec/__init__.py
eudtrg/base/dataspec/bytedump.py
eudtrg/base/dataspec/eudobj.py
eudtrg/base/dataspec/expr.py
eudtrg/base/dataspec/forward.py
eudtrg/base/dataspec/rlocint.py
eudtrg/base/dataspec/struoffset.py
eudtrg/base/dataspec/trigger.py
eudtrg/base/mapdata/SFmpq.dll
eudtrg/base/mapdata/__init__.py
eudtrg/base/mapdata/chktok.py
eudtrg/base/mapdata/doevents.py
eudtrg/base/mapdata/injgen.py
eudtrg/base/mapdata/mapdata.py
eudtrg/base/mapdata/maprw.py
eudtrg/base/mapdata/mpqapi.py
eudtrg/base/mapdata/nametable.py
eudtrg/base/mapdata/prptable.py
eudtrg/base/mapdata/trigtrg.py
eudtrg/base/mapdata/unitprp.py
eudtrg/base/payload/__init__.py
eudtrg/base/payload/depgraph.py
eudtrg/base/payload/payload.py
eudtrg/base/utils/__init__.py
eudtrg/base/utils/binio.py
eudtrg/base/utils/sctbl.py
eudtrg/base/utils/ubconv.py
eudtrg/base/utils/utils.py
eudtrg/lib/__init__.py
eudtrg/lib/auxfunc/__init__.py
eudtrg/lib/auxfunc/constmuldiv.py
eudtrg/lib/auxfunc/dwordbreak.py
eudtrg/lib/auxfunc/epdcalc.py
eudtrg/lib/auxfunc/expfunc.py
eudtrg/lib/auxfunc/memcpy.py
eudtrg/lib/auxfunc/muldiv.py
eudtrg/lib/auxfunc/readdword.py
eudtrg/lib/auxfunc/setcurpl.py
eudtrg/lib/auxfunc/writedword.py
eudtrg/lib/auxobj/__init__.py
eudtrg/lib/auxobj/eudgrp.py
eudtrg/lib/auxobj/eudtbl.py
eudtrg/lib/baselib/__init__.py
eudtrg/lib/baselib/blockstru.py
eudtrg/lib/baselib/ctrlstru.py
eudtrg/lib/baselib/eudfunc.py
eudtrg/lib/baselib/vtable.py