Metadata-Version: 1.0
Name: eudtrg
Version: 0.30-r2-beta
Summary: EUD Trigger generator
Home-page: http://blog.naver.com/whyask37/
Author: Trgk
Author-email: whyask37@naver.com
License: zlib license
Keywords: starcraft trigger eud
Platform: UNKNOWN
